<?xml version="1.1" encoding="UTF-8"?>
<expression:EMFExpression xmi:version="2.0" xmlns:xmi="http://www.omg.org/XMI" xmlns:expression="http:///expression.ecore" id="tMap_3=>" expression="Relational.ISNULL(row7.VAL_SH_FED) ? 0.0 : row7.VAL_SH_FED">
  <variables name="row7.UF_ZI" value="null" talendType="id_String" nullable="true"/>
  <variables name="row7.ANO_CMPT" value="null" talendType="id_String" nullable="true"/>
  <variables name="row7.MES_CMPT" value="null" talendType="id_String" nullable="true"/>
  <variables name="row7.ESPEC" value="null" talendType="id_String" nullable="true"/>
  <variables name="row7.CGC_HOSP" value="null" talendType="id_String" nullable="true"/>
  <variables name="row7.N_AIH" value="null" talendType="id_String" nullable="true"/>
  <variables name="row7.IDENT" value="null" talendType="id_String" nullable="true"/>
  <variables name="row7.CEP" value="null" talendType="id_String" nullable="true"/>
  <variables name="row7.MUNIC_RES" value="null" talendType="id_String" nullable="true"/>
  <variables name="row7.NASC" value="null" talendType="id_String" nullable="true"/>
  <variables name="row7.SEXO" value="null" talendType="id_String" nullable="true"/>
  <variables name="row7.UTI_MES_IN" value="null" talendType="id_Double" nullable="true"/>
  <variables name="row7.UTI_MES_AN" value="null" talendType="id_Double" nullable="true"/>
  <variables name="row7.UTI_MES_AL" value="null" talendType="id_Double" nullable="true"/>
  <variables name="row7.UTI_MES_TO" value="null" talendType="id_Double" nullable="true"/>
  <variables name="row7.MARCA_UTI" value="null" talendType="id_String" nullable="true"/>
  <variables name="row7.UTI_INT_IN" value="null" talendType="id_Double" nullable="true"/>
  <variables name="row7.UTI_INT_AN" value="null" talendType="id_Double" nullable="true"/>
  <variables name="row7.UTI_INT_AL" value="null" talendType="id_Double" nullable="true"/>
  <variables name="row7.UTI_INT_TO" value="null" talendType="id_Double" nullable="true"/>
  <variables name="row7.DIAR_ACOM" value="null" talendType="id_Double" nullable="true"/>
  <variables name="row7.QT_DIARIAS" value="null" talendType="id_Double" nullable="true"/>
  <variables name="row7.PROC_SOLIC" value="null" talendType="id_String" nullable="true"/>
  <variables name="row7.PROC_REA" value="null" talendType="id_String" nullable="true"/>
  <variables name="row7.VAL_SH" value="null" talendType="id_Double" nullable="true"/>
  <variables name="row7.VAL_SP" value="null" talendType="id_Double" nullable="true"/>
  <variables name="row7.VAL_SADT" value="null" talendType="id_Double" nullable="true"/>
  <variables name="row7.VAL_RN" value="null" talendType="id_Double" nullable="true"/>
  <variables name="row7.VAL_ACOMP" value="null" talendType="id_Double" nullable="true"/>
  <variables name="row7.VAL_ORTP" value="null" talendType="id_Double" nullable="true"/>
  <variables name="row7.VAL_SANGUE" value="null" talendType="id_Double" nullable="true"/>
  <variables name="row7.VAL_SADTSR" value="null" talendType="id_Double" nullable="true"/>
  <variables name="row7.VAL_TRANSP" value="null" talendType="id_Double" nullable="true"/>
  <variables name="row7.VAL_OBSANG" value="null" talendType="id_Double" nullable="true"/>
  <variables name="row7.VAL_PED1AC" value="null" talendType="id_Double" nullable="true"/>
  <variables name="row7.VAL_TOT" value="null" talendType="id_Double" nullable="true"/>
  <variables name="row7.VAL_UTI" value="null" talendType="id_Double" nullable="true"/>
  <variables name="row7.US_TOT" value="null" talendType="id_Double" nullable="true"/>
  <variables name="row7.DT_INTER" value="null" talendType="id_String" nullable="true"/>
  <variables name="row7.DT_SAIDA" value="null" talendType="id_String" nullable="true"/>
  <variables name="row7.DIAG_PRINC" value="null" talendType="id_String" nullable="true"/>
  <variables name="row7.DIAG_SECUN" value="null" talendType="id_String" nullable="true"/>
  <variables name="row7.COBRANCA" value="null" talendType="id_String" nullable="true"/>
  <variables name="row7.NATUREZA" value="null" talendType="id_String" nullable="true"/>
  <variables name="row7.NAT_JUR" value="null" talendType="id_String" nullable="true"/>
  <variables name="row7.GESTAO" value="null" talendType="id_String" nullable="true"/>
  <variables name="row7.RUBRICA" value="null" talendType="id_Double" nullable="true"/>
  <variables name="row7.IND_VDRL" value="null" talendType="id_String" nullable="true"/>
  <variables name="row7.MUNIC_MOV" value="null" talendType="id_String" nullable="true"/>
  <variables name="row7.COD_IDADE" value="null" talendType="id_String" nullable="true"/>
  <variables name="row7.IDADE" value="null" talendType="id_Double" nullable="true"/>
  <variables name="row7.DIAS_PERM" value="null" talendType="id_Double" nullable="true"/>
  <variables name="row7.MORTE" value="null" talendType="id_Double" nullable="true"/>
  <variables name="row7.NACIONAL" value="null" talendType="id_String" nullable="true"/>
  <variables name="row7.NUM_PROC" value="null" talendType="id_String" nullable="true"/>
  <variables name="row7.CAR_INT" value="null" talendType="id_String" nullable="true"/>
  <variables name="row7.TOT_PT_SP" value="null" talendType="id_Double" nullable="true"/>
  <variables name="row7.CPF_AUT" value="null" talendType="id_String" nullable="true"/>
  <variables name="row7.HOMONIMO" value="null" talendType="id_String" nullable="true"/>
  <variables name="row7.NUM_FILHOS" value="null" talendType="id_Double" nullable="true"/>
  <variables name="row7.INSTRU" value="null" talendType="id_String" nullable="true"/>
  <variables name="row7.CID_NOTIF" value="null" talendType="id_String" nullable="true"/>
  <variables name="row7.CONTRACEP1" value="null" talendType="id_String" nullable="true"/>
  <variables name="row7.CONTRACEP2" value="null" talendType="id_String" nullable="true"/>
  <variables name="row7.GESTRISCO" value="null" talendType="id_String" nullable="true"/>
  <variables name="row7.INSC_PN" value="null" talendType="id_String" nullable="true"/>
  <variables name="row7.SEQ_AIH5" value="null" talendType="id_String" nullable="true"/>
  <variables name="row7.CBOR" value="null" talendType="id_String" nullable="true"/>
  <variables name="row7.CNAER" value="null" talendType="id_String" nullable="true"/>
  <variables name="row7.VINCPREV" value="null" talendType="id_String" nullable="true"/>
  <variables name="row7.GESTOR_COD" value="null" talendType="id_String" nullable="true"/>
  <variables name="row7.GESTOR_TP" value="null" talendType="id_String" nullable="true"/>
  <variables name="row7.GESTOR_CPF" value="null" talendType="id_String" nullable="true"/>
  <variables name="row7.GESTOR_DT" value="null" talendType="id_String" nullable="true"/>
  <variables name="row7.CNES" value="null" talendType="id_String" nullable="true"/>
  <variables name="row7.CNPJ_MANT" value="null" talendType="id_String" nullable="true"/>
  <variables name="row7.INFEHOSP" value="null" talendType="id_String" nullable="true"/>
  <variables name="row7.CID_ASSO" value="null" talendType="id_String" nullable="true"/>
  <variables name="row7.CID_MORTE" value="null" talendType="id_String" nullable="true"/>
  <variables name="row7.COMPLEX" value="null" talendType="id_String" nullable="true"/>
  <variables name="row7.FINANC" value="null" talendType="id_String" nullable="true"/>
  <variables name="row7.FAEC_TP" value="null" talendType="id_String" nullable="true"/>
  <variables name="row7.REGCT" value="null" talendType="id_String" nullable="true"/>
  <variables name="row7.RACA_COR" value="null" talendType="id_String" nullable="true"/>
  <variables name="row7.ETNIA" value="null" talendType="id_String" nullable="true"/>
  <variables name="row7.SEQUENCIA" value="null" talendType="id_Double" nullable="true"/>
  <variables name="row7.REMESSA" value="null" talendType="id_String" nullable="true"/>
  <variables name="row7.AUD_JUST" value="null" talendType="id_String" nullable="true"/>
  <variables name="row7.SIS_JUST" value="null" talendType="id_String" nullable="true"/>
  <variables name="row7.VAL_SH_FED" value="null" talendType="id_Double" nullable="true"/>
  <variables name="row7.VAL_SP_FED" value="null" talendType="id_Double" nullable="true"/>
  <variables name="row7.VAL_SH_GES" value="null" talendType="id_Double" nullable="true"/>
  <variables name="row7.VAL_SP_GES" value="null" talendType="id_Double" nullable="true"/>
  <variables name="row7.VAL_UCI" value="null" talendType="id_Double" nullable="true"/>
  <variables name="row7.MARCA_UCI" value="null" talendType="id_String" nullable="true"/>
  <variables name="row7.SEXOC" value="null" talendType="id_String" nullable="true"/>
  <variables name="row7.IDADEF" value="null" talendType="id_Double" nullable="true"/>
</expression:EMFExpression>
